Metadata-Version: 2.1
Name: liverecs-tahoee-client
Version: 5.0.56
Summary: Security research package
Home-page: UNKNOWN
Author: whybee
Author-email: whybee@wearehackerone.com
License: UNKNOWN
Platform: UNKNOWN
Classifier: Programming Language :: Python :: 3
Classifier: Programming Language :: Python :: 2
